{"text":"delete1","category":"Delete","userId":"vI1GMkzBza5i82zj","_id":"31jxoqNzFcTW2J2g"}
{"text":"new task","category":"Delegate","userId":"vI1GMkzBza5i82zj","_id":"4CeJTv5G4R8Kw6kO"}
{"text":"new task 3","category":"Do","userId":"vI1GMkzBza5i82zj","_id":"9C0zLl9strHqOJp5"}
{"text":"b's task","category":"Do","userId":"vI1GMkzBza5i82zz","_id":"FMeHK0xR1w8v37Vh"}
{"text":"new task nov 8","category":"Decide","userId":"vI1GMkzBza5i82zj","_id":"JCHKo6R3ybp0onoI"}
{"text":"some task to delete","category":"Delete","userId":"vI1GMkzBza5i82zj","_id":"ZiqLPZS85134vC6y"}
{"text":"new task 2","category":"Decide","userId":"vI1GMkzBza5i82zj","_id":"dKFTGgyzQ4Ld5SNz"}
{"text":"b's other task","category":"Delegate","userId":"vI1GMkzBza5i82zz","_id":"lOD04uTNrQXVMPaE"}
{"text":"new task 4","category":"Do","userId":"vI1GMkzBza5i82zj","_id":"pJ5I0d3oee4Iykok"}
{"text":"delete2","category":"Delete","userId":"vI1GMkzBza5i82zj","_id":"3XXzDB5X4cJqfP33"}
{"text":"delete3","category":"Delete","userId":"vI1GMkzBza5i82zj","_id":"rD0Kj3r6pUcIFSmq"}
{"text":"delete4","category":"Delete","userId":"vI1GMkzBza5i82zj","_id":"mQTVtSDhUyUgWT1j"}
{"text":"delete5","category":"Delete","userId":"vI1GMkzBza5i82zj","_id":"RgeojTcFuwlv7owU"}
{"text":"delegate1","category":"Delegate","userId":"vI1GMkzBza5i82zj","_id":"WrTBvqsgifNhStPi"}
{"text":"delegate2","category":"Delete","userId":"vI1GMkzBza5i82zj","_id":"uT2IEmoXvbhY47Ct"}
{"text":"delegate3","category":"Delegate","userId":"vI1GMkzBza5i82zj","_id":"QNjTzI5aTPhgEygr"}
{"text":"do1","category":"Do","userId":"vI1GMkzBza5i82zj","_id":"2I2W8hWADMNtvDHp"}
